comcomdrive/__init__.py
comcomdrive/auth.py
comcomdrive/cli_tools.py
comcomdrive/search.py
comcomdrive/settings.py
comcomdrive/transfer.py
comcomdrive-0.0.6.dist-info/LICENSE
comcomdrive-0.0.6.dist-info/METADATA
comcomdrive-0.0.6.dist-info/WHEEL
comcomdrive-0.0.6.dist-info/entry_points.txt
comcomdrive-0.0.6.dist-info/top_level.txt
comcomdrive-0.0.6.dist-info/RECORD
